guiqwt303/__init__.py
guiqwt303/_cm.py
guiqwt303/_scaler.cp310-win_amd64.pyd
guiqwt303/annotations.py
guiqwt303/baseplot.py
guiqwt303/builder.py
guiqwt303/colormap.py
guiqwt303/config.py
guiqwt303/cross_section.py
guiqwt303/curve.py
guiqwt303/debug.py
guiqwt303/events.py
guiqwt303/geometry.py
guiqwt303/histogram.py
guiqwt303/histogram2d.cp310-win_amd64.pyd
guiqwt303/image.py
guiqwt303/interfaces.py
guiqwt303/io.py
guiqwt303/label.py
guiqwt303/mandelbrot.cp310-win_amd64.pyd
guiqwt303/panels.py
guiqwt303/plot.py
guiqwt303/pyplot.py
guiqwt303/qtdesigner.py
guiqwt303/qthelpers.py
guiqwt303/scaler.py
guiqwt303/shapes.py
guiqwt303/signals.py
guiqwt303/styles.py
guiqwt303/tools.py
guiqwt303/transitional.py
guiqwt303/images/arrow_down.png
guiqwt303/images/arrow_up.png
guiqwt303/images/autorefresh.png
guiqwt303/images/axes.png
guiqwt303/images/center.png
guiqwt303/images/contrast.png
guiqwt303/images/copytoclipboard.png
guiqwt303/images/csapplylut.png
guiqwt303/images/csautoscale.png
guiqwt303/images/csection.png
guiqwt303/images/csection_a.png
guiqwt303/images/csection_oblique.png
guiqwt303/images/csperimage.png
guiqwt303/images/eliminate_outliers.png
guiqwt303/images/eraser.png
guiqwt303/images/export.png
guiqwt303/images/font.png
guiqwt303/images/full_range.png
guiqwt303/images/funct.png
guiqwt303/images/guiqwt.svg
guiqwt303/images/hcursor.png
guiqwt303/images/hflip.png
guiqwt303/images/imagestats.png
guiqwt303/images/item_list.png
guiqwt303/images/magnifier.png
guiqwt303/images/move.png
guiqwt303/images/on_curve.png
guiqwt303/images/point_selection.png
guiqwt303/images/print.png
guiqwt303/images/refresh.png
guiqwt303/images/sift.svg
guiqwt303/images/snapshot.png
guiqwt303/images/trash.png
guiqwt303/images/vcursor.png
guiqwt303/images/vflip.png
guiqwt303/images/xcursor.png
guiqwt303/images/xrange.png
guiqwt303/images/curvestyles/dots.png
guiqwt303/images/curvestyles/lines.png
guiqwt303/images/curvestyles/steps.png
guiqwt303/images/curvestyles/sticks.png
guiqwt303-3.0.3.post4.dist-info/Licence_CeCILL_V2-en.txt
guiqwt303-3.0.3.post4.dist-info/METADATA
guiqwt303-3.0.3.post4.dist-info/WHEEL
guiqwt303-3.0.3.post4.dist-info/entry_points.txt
guiqwt303-3.0.3.post4.dist-info/top_level.txt
guiqwt303-3.0.3.post4.dist-info/RECORD
